zhlib_snapshot/__init__.py
zhlib_snapshot/db.py
zhlib_snapshot/dict.db
zhlib_snapshot/level.py
zhlib_snapshot/util.py
zhlib_snapshot-0.1.2.1.dist-info/WHEEL
zhlib_snapshot-0.1.2.1.dist-info/METADATA
zhlib_snapshot-0.1.2.1.dist-info/RECORD
