Metadata-Version: 2.1
Name: zhlib-snapshot
Version: 0.1.2.1
Summary: Snapshot of zhlib: Dictionaries and what to learn in Chinese
Home-page: UNKNOWN
License: MIT
Author: Pacharapol Withayasakpunt
Author-email: patarapolw@gmail.com
Classifier: License :: OSI Approved :: MIT License
Classifier: Programming Language :: Python :: 2
Classifier: Programming Language :: Python :: 2.7
Classifier: Programming Language :: Python :: 3
Classifier: Programming Language :: Python :: 3.4
Classifier: Programming Language :: Python :: 3.5
Classifier: Programming Language :: Python :: 3.6
Classifier: Programming Language :: Python :: 3.7
Requires-Dist: jieba (>=0.39.0,<0.40.0)
Requires-Dist: peewee (>=3.7,<4.0)
Requires-Dist: regex (==2018.02.21)
Requires-Dist: wordfreq (>=2.2,<3.0)
